pyhibp/__init__.py
pyhibp/__version__.py
pyhibp/pwnedpasswords.py
pyhibp-4.2.0.dist-info/LICENSE
pyhibp-4.2.0.dist-info/METADATA
pyhibp-4.2.0.dist-info/WHEEL
pyhibp-4.2.0.dist-info/top_level.txt
pyhibp-4.2.0.dist-info/RECORD
